aiopaykassa/__init__.py
aiopaykassa/clients/__init__.py
aiopaykassa/clients/api.py
aiopaykassa/clients/base/__init__.py
aiopaykassa/clients/base/api.py
aiopaykassa/clients/base/base.py
aiopaykassa/clients/base/sci.py
aiopaykassa/clients/sci.py
aiopaykassa/endpoints/__init__.py
aiopaykassa/endpoints/api/__init__.py
aiopaykassa/endpoints/api/currency_rate.py
aiopaykassa/endpoints/api/get_shop_balance.py
aiopaykassa/endpoints/api/payment.py
aiopaykassa/endpoints/base.py
aiopaykassa/endpoints/sci/__init__.py
aiopaykassa/endpoints/sci/confirm_order.py
aiopaykassa/endpoints/sci/confirm_transaction_notification.py
aiopaykassa/endpoints/sci/create_order.py
aiopaykassa/endpoints/sci/create_order_get_data.py
aiopaykassa/enums.py
aiopaykassa/exceptions.py
aiopaykassa/types/__init__.py
aiopaykassa/types/base.py
aiopaykassa/types/confirmed_order.py
aiopaykassa/types/currency_rate.py
aiopaykassa/types/new_order.py
aiopaykassa/types/new_order_data.py
aiopaykassa/types/payment.py
aiopaykassa/types/shop_balance.py
aiopaykassa/types/transaction_notification.py
aiopaykassa/utils/__init__.py
aiopaykassa/utils/json.py
LICENSE
aiopaykassa-0.0.1a3.dist-info/LICENSE
aiopaykassa-0.0.1a3.dist-info/WHEEL
aiopaykassa-0.0.1a3.dist-info/METADATA
aiopaykassa-0.0.1a3.dist-info/RECORD
