Metadata-Version: 2.1
Name: aiopaykassa
Version: 0.0.1a3
Summary: Paykassa.pro asyncio python client
Home-page: https://github.com/drforse/aiopaykassa
License: MIT
Author: drforse
Author-email: george.lifeslice@gmail.com
Requires-Python: >=3.10,<4.0
Classifier: Framework :: AsyncIO
Classifier: Framework :: aiohttp
Classifier: License :: OSI Approved :: MIT License
Classifier: Operating System :: OS Independent
Classifier: Programming Language :: Python :: 3
Classifier: Programming Language :: Python :: 3.10
Provides-Extra: ujson
Requires-Dist: aiohttp (>=3.8.1,<4.0.0)
Requires-Dist: pydantic (>=1.9.0,<2.0.0)
Requires-Dist: ujson (>=5.2.0,<6.0.0); extra == "ujson"
Project-URL: Repository, https://github.com/drforse/aiopaykassa
